LICENSE
MANIFEST.in
README.md
setup.py
composition_vectorizer/__init__.py
composition_vectorizer/featurizers.py
composition_vectorizer/utilities.py
composition_vectorizer/version.py
composition_vectorizer.egg-info/PKG-INFO
composition_vectorizer.egg-info/SOURCES.txt
composition_vectorizer.egg-info/dependency_links.txt
composition_vectorizer.egg-info/requires.txt
composition_vectorizer.egg-info/top_level.txt
composition_vectorizer/Files_from_GTDL_paper/Z_row_column.txt
composition_vectorizer/Files_from_GTDL_paper/element_property.txt
composition_vectorizer/Files_from_GTDL_paper/gao_data.txt
composition_vectorizer/Files_from_GTDL_paper/gfa_dataset.txt
composition_vectorizer/__pycache__/__init__.cpython-310.pyc
composition_vectorizer/__pycache__/d1.cpython-310.pyc
composition_vectorizer/__pycache__/featurizers.cpython-310.pyc
composition_vectorizer/__pycache__/utilities.cpython-310.pyc
composition_vectorizer/__pycache__/version.cpython-310.pyc
composition_vectorizer/orderings/1d_orderings.pkl